fanficapi/__init_.py
fanficapi/__init__.py
fanficapi/fanficapi.py
fanficapi/ao3essentials/author.py
fanficapi/ao3essentials/errors.py
fanficapi/ao3essentials/story.py
fanficapi/ffnessentials/author.py
fanficapi/ffnessentials/errors.py
fanficapi/ffnessentials/story.py
fanficapi-1.0.5.dist-info/LICENSE
fanficapi-1.0.5.dist-info/METADATA
fanficapi-1.0.5.dist-info/WHEEL
fanficapi-1.0.5.dist-info/top_level.txt
fanficapi-1.0.5.dist-info/RECORD
