Metadata-Version: 2.1
Name: fanficapi
Version: 1.0.5
Summary: Metadata scraper for FFN and AO3
Home-page: UNKNOWN
Author: lonely-code-cube
License: UNKNOWN
Keywords: python,scraper,webscraper,metadata scraper,fanfiction,archiveofourown,fanfic scraper,fanfic api
Platform: UNKNOWN
Classifier: Development Status :: 1 - Planning
Classifier: Intended Audience :: Developers
Classifier: Programming Language :: Python :: 3
Classifier: Operating System :: Unix
Classifier: Operating System :: MacOS :: MacOS X
Classifier: Operating System :: Microsoft :: Windows
Requires-Dist: bs4
Requires-Dist: requests
Requires-Dist: undetected-chromedriver
